<?xml version = '1.0' encoding = 'UTF-8'?>
<Relation class="oracle.dbtools.crest.model.design.logical.Relation" name="Relation_19" directorySegmentName="seg_0" id="B0E547A9-9A9B-9298-9486-408AF0877EA8">
<createdBy>esneyder</createdBy>
<createdTime>2020-06-09 21:23:56 UTC</createdTime>
<ownerDesignName>modeloER</ownerDesignName>
<engineerTo>
<item key="6A89F0E5-EF98-B660-3A33-F2060467327A" value="true"/>
</engineerTo>
<sourcePk>7BE008C5-9BC7-6F25-222C-CACFD5E3B1D6</sourcePk>
<identifying>false</identifying>
<optionalSource>true</optionalSource>
<optionalTarget>false</optionalTarget>
<sourceCardinality>1</sourceCardinality>
<sourceEntity>B0A44477-6A0B-2F5E-AE29-EAA1D5E0BBEE</sourceEntity>
<targetCardinalityString>*</targetCardinalityString>
<targetEntity>71372C23-E70F-D8EA-9FE3-181F550A4C0A</targetEntity>
<transferable>true</transferable>
<deleteRule>NO ACTION</deleteRule>
</Relation>
